nbforager/__init__.py
nbforager/api/__init__.py
nbforager/api/base_c.py
nbforager/api/base_ca.py
nbforager/api/circuits.py
nbforager/api/connector.py
nbforager/api/core.py
nbforager/api/dcim.py
nbforager/api/extended_get.py
nbforager/api/extras.py
nbforager/api/ip_addresses.py
nbforager/api/ipam.py
nbforager/api/plugins_ca.py
nbforager/api/status.py
nbforager/api/tenancy.py
nbforager/api/users.py
nbforager/api/virtualization.py
nbforager/api/wireless.py
nbforager/exceptions.py
nbforager/foragers/__init__.py
nbforager/foragers/base_fa.py
nbforager/foragers/circuits.py
nbforager/foragers/core.py
nbforager/foragers/dcim.py
nbforager/foragers/extras.py
nbforager/foragers/forager.py
nbforager/foragers/ipam.py
nbforager/foragers/ipv4.py
nbforager/foragers/joiner.py
nbforager/foragers/tenancy.py
nbforager/foragers/users.py
nbforager/foragers/virtualization.py
nbforager/foragers/wireless.py
nbforager/helpers.py
nbforager/log.py
nbforager/messages.py
nbforager/nb_api.py
nbforager/nb_cache.py
nbforager/nb_forager.py
nbforager/nb_tree.py
nbforager/parser/__init__.py
nbforager/parser/nb_custom.py
nbforager/parser/nb_parser.py
nbforager/parser/nb_value.py
nbforager/py.typed
nbforager/py_tree.py
nbforager/types_.py
nbforager-0.2.4.dist-info/LICENCE.txt
nbforager-0.2.4.dist-info/METADATA
nbforager-0.2.4.dist-info/WHEEL
nbforager-0.2.4.dist-info/RECORD
