Metadata-Version: 2.1
Name: nbforager
Version: 0.2.4
Summary: Python package designed to assist in working with the Netbox REST API. The filter parameters are identical to those in the Web UI filter form. It replaces brief data with full information, and Netbox objects are represented as a recursive multidimensional dictionary.
Home-page: https://github.com/vladimirs-git/nbforager
License: Apache-2.0
Keywords: netbox
Author: Vladimirs Prusakovs
Author-email: vladimir.prusakovs@gmail.com
Requires-Python: >=3.8,<4.0
Classifier: Development Status :: 5 - Production/Stable
Classifier: Intended Audience :: Developers
Classifier: License :: OSI Approved :: Apache Software License
Classifier: Natural Language :: English
Classifier: Programming Language :: Python :: 3
Classifier: Programming Language :: Python :: 3.8
Classifier: Programming Language :: Python :: 3.9
Classifier: Programming Language :: Python :: 3.10
Classifier: Programming Language :: Python :: 3.11
Classifier: Programming Language :: Python :: 3.12
Provides-Extra: test
Requires-Dist: ciscoconfparse (>=1.9,<2.0)
Requires-Dist: netports (>=0.12.1,<1.0.0)
Requires-Dist: pydantic (>=2,<3)
Requires-Dist: pynetbox (>=7.3.3,<8.0.0)
Requires-Dist: requests (>=2,<3)
Requires-Dist: tabulate (>=0.9.0,<0.10.0)
Requires-Dist: tomli (==2.0.1)
Requires-Dist: vhelpers (>=0.1,<1.0.0)
Project-URL: Bug Tracker, https://github.com/vladimirs-git/nbforager/issues
Project-URL: Download URL, https://github.com/vladimirs-git/nbforager/archive/refs/tags/0.2.4.tar.gz
Project-URL: Repository, https://github.com/vladimirs-git/nbforager
